llama_index/callbacks/arize_phoenix/__init__.py
llama_index/callbacks/arize_phoenix/base.py
llama_index_callbacks_arize_phoenix-0.6.0.dist-info/METADATA
llama_index_callbacks_arize_phoenix-0.6.0.dist-info/WHEEL
llama_index_callbacks_arize_phoenix-0.6.0.dist-info/licenses/LICENSE
llama_index_callbacks_arize_phoenix-0.6.0.dist-info/RECORD
