Metadata-Version: 2.4
Name: llama-index-callbacks-arize-phoenix
Version: 0.6.0
Summary: llama-index callbacks arize-phoenix integration
Author-email: Arize AI <phoenix-devs@arize.com>, OpenInference Authors <oss@arize.com>
License-Expression: MIT
License-File: LICENSE
Requires-Python: <3.14,>=3.9
Requires-Dist: llama-index-core<0.14,>=0.13.0
Requires-Dist: openinference-instrumentation-llama-index>=4.1.0
